{
  "data": [
    {
      "ID": 1,
      "Type": 0,
      "Chapter": 1,
      "Section": "0,1",
      "Wave1": "111:2",
      "Duration1": 6,
      "Wave2": "",
      "Duration2": "",
      "Wave3": "",
      "Duration3": "",
      "SuddenWave": "",
      "Duration4": "",
      "HPValue": 1,
      "DamageValue": 1
    },
    {
      "ID": 2,
      "Type": 0,
      "Chapter": 1,
      "Section": "0,1",
      "Wave1": "112:3",
      "Duration1": 6,
      "Wave2": "",
      "Duration2": "",
      "Wave3": "",
      "Duration3": "",
      "SuddenWave": "",
      "Duration4": "",
      "HPValue": 1,
      "DamageValue": 1
    },
    {
      "ID": 3,
      "Type": 0,
      "Chapter": 1,
      "Section": "0,1",
      "Wave1": "113:1",
      "Duration1": 6,
      "Wave2": "",
      "Duration2": "",
      "Wave3": "",
      "Duration3": "",
      "SuddenWave": "",
      "Duration4": "",
      "HPValue": 1,
      "DamageValue": 1
    },
    {
      "ID": 4,
      "Type": 0,
      "Chapter": 1,
      "Section": "2,3",
      "Wave1": "111:2,112:2",
      "Duration1": 6,
      "Wave2": "111:1,113:1",
      "Duration2": 6,
      "Wave3": "",
      "Duration3": "",
      "SuddenWave": "",
      "Duration4": "",
      "HPValue": 1,
      "DamageValue": 1
    },
    {
      "ID": 5,
      "Type": 0,
      "Chapter": 1,
      "Section": "2,3",
      "Wave1": "121:2,122:2",
      "Duration1": 6,
      "Wave2": "121:1,123:1",
      "Duration2": 6,
      "Wave3": "",
      "Duration3": "",
      "SuddenWave": "",
      "Duration4": "",
      "HPValue": 1,
      "DamageValue": 1
    },
    {
      "ID": 6,
      "Type": 0,
      "Chapter": 1,
      "Section": "2,3",
      "Wave1": "111:2,112:2",
      "Duration1": 6,
      "Wave2": "121:2,122:2",
      "Duration2": 6,
      "Wave3": "",
      "Duration3": "",
      "SuddenWave": "",
      "Duration4": "",
      "HPValue": 1,
      "DamageValue": 1
    },
    {
      "ID": 7,
      "Type": 0,
      "Chapter": 1,
      "Section": "4,6",
      "Wave1": "111:4,112:4",
      "Duration1": 6,
      "Wave2": "111:2,113:3",
      "Duration2": 6,
      "Wave3": "",
      "Duration3": "",
      "SuddenWave": "",
      "Duration4": "",
      "HPValue": 1,
      "DamageValue": 1
    },
    {
      "ID": 8,
      "Type": 0,
      "Chapter": 1,
      "Section": "4,6",
      "Wave1": "121:4,122:4",
      "Duration1": 6,
      "Wave2": "121:2,123:3",
      "Duration2": 6,
      "Wave3": "",
      "Duration3": "",
      "SuddenWave": "",
      "Duration4": "",
      "HPValue": 1,
      "DamageValue": 1
    },
    {
      "ID": 9,
      "Type": 0,
      "Chapter": 1,
      "Section": "4,6",
      "Wave1": "151:4,122:5",
      "Duration1": 6,
      "Wave2": "151:3,123:1",
      "Duration2": 6,
      "Wave3": "",
      "Duration3": "",
      "SuddenWave": "",
      "Duration4": "",
      "HPValue": 1,
      "DamageValue": 1
    },
    {
      "ID": 10,
      "Type": 0,
      "Chapter": 1,
      "Section": "7,9",
      "Wave1": "111:5,112:5",
      "Duration1": 6,
      "Wave2": "121:4,122:5",
      "Duration2": 6,
      "Wave3": "113:3,123:2",
      "Duration3": 6,
      "SuddenWave": "",
      "Duration4": "",
      "HPValue": 1,
      "DamageValue": 1
    },
    {
      "ID": 11,
      "Type": 0,
      "Chapter": 1,
      "Section": "7,9",
      "Wave1": "121:9,122:7",
      "Duration1": 6,
      "Wave2": "121:4,123:3",
      "Duration2": 6,
      "Wave3": "",
      "Duration3": "",
      "SuddenWave": "",
      "Duration4": "",
      "HPValue": 1,
      "DamageValue": 1
    },
    {
      "ID": 12,
      "Type": 0,
      "Chapter": 1,
      "Section": "7,9",
      "Wave1": "151:8,161:7",
      "Duration1": 6,
      "Wave2": "151:6,161:5",
      "Duration2": 6,
      "Wave3": "",
      "Duration3": "",
      "SuddenWave": "",
      "Duration4": "",
      "HPValue": 1,
      "DamageValue": 1
    },
    {
      "ID": 13,
      "Type": "0",
      "Chapter": "1",
      "Section": "10",
      "Wave1": "111:8,112:7",
      "Duration1": 6,
      "Wave2": "121:6,122:6",
      "Duration2": 6,
      "Wave3": "113:4,123:3",
      "Duration3": "6",
      "SuddenWave": "",
      "Duration4": "",
      "HPValue": 1,
      "DamageValue": "1"
    },
    {
      "ID": 14,
      "Type": "0",
      "Chapter": "1",
      "Section": "10",
      "Wave1": "121:11,122:9",
      "Duration1": 6,
      "Wave2": "151:10,123:4",
      "Duration2": 6,
      "Wave3": "",
      "Duration3": "",
      "SuddenWave": "",
      "Duration4": "",
      "HPValue": 1,
      "DamageValue": "1"
    },
    {
      "ID": 15,
      "Type": "0",
      "Chapter": "2",
      "Section": "0,3",
      "Wave1": "131:10,132:10",
      "Duration1": 6,
      "Wave2": "131:9,133:3",
      "Duration2": 6,
      "Wave3": "",
      "Duration3": "",
      "SuddenWave": "",
      "Duration4": "",
      "HPValue": 1,
      "DamageValue": "1"
    },
    {
      "ID": 16,
      "Type": "0",
      "Chapter": "2",
      "Section": "0,3",
      "Wave1": "141:9,142:8",
      "Duration1": 6,
      "Wave2": "141:5,143:3",
      "Duration2": 6,
      "Wave3": "",
      "Duration3": "",
      "SuddenWave": "",
      "Duration4": "",
      "HPValue": 1,
      "DamageValue": "1"
    },
    {
      "ID": 17,
      "Type": "0",
      "Chapter": "2",
      "Section": "0,3",
      "Wave1": "151:15,161:13",
      "Duration1": 6,
      "Wave2": "151:11,161:9",
      "Duration2": 6,
      "Wave3": "",
      "Duration3": "",
      "SuddenWave": "",
      "Duration4": "",
      "HPValue": 1,
      "DamageValue": "1"
    },
    {
      "ID": 18,
      "Type": "0",
      "Chapter": "2",
      "Section": "4,6",
      "Wave1": "131:10,132:10",
      "Duration1": 6,
      "Wave2": "133:5,161:13",
      "Duration2": 6,
      "Wave3": "",
      "Duration3": "",
      "SuddenWave": "",
      "Duration4": "",
      "HPValue": 1,
      "DamageValue": "1"
    },
    {
      "ID": 19,
      "Type": "0",
      "Chapter": "2",
      "Section": "4,6",
      "Wave1": "141:11,142:10",
      "Duration1": 6,
      "Wave2": "143:6,151:13",
      "Duration2": 6,
      "Wave3": "",
      "Duration3": "",
      "SuddenWave": "",
      "Duration4": "",
      "HPValue": 1,
      "DamageValue": "1"
    },
    {
      "ID": 20,
      "Type": "0",
      "Chapter": "2",
      "Section": "4,6",
      "Wave1": "305:15,306:15",
      "Duration1": 6,
      "Wave2": "313:12,314:11",
      "Duration2": 6,
      "Wave3": "",
      "Duration3": "",
      "SuddenWave": "",
      "Duration4": "",
      "HPValue": 1,
      "DamageValue": "1"
    },
    {
      "ID": 21,
      "Type": "0",
      "Chapter": "2",
      "Section": "7,9",
      "Wave1": "313:30,314:30",
      "Duration1": 6,
      "Wave2": "131:10,132:10",
      "Duration2": 6,
      "Wave3": "",
      "Duration3": "",
      "SuddenWave": "",
      "Duration4": "",
      "HPValue": 1.2,
      "DamageValue": "1"
    },
    {
      "ID": 22,
      "Type": "0",
      "Chapter": "2",
      "Section": "7,9",
      "Wave1": "131:15,132:15",
      "Duration1": 6,
      "Wave2": "133:8,161:17",
      "Duration2": 6,
      "Wave3": "",
      "Duration3": "",
      "SuddenWave": "",
      "Duration4": "",
      "HPValue": 1.2,
      "DamageValue": "1"
    },
    {
      "ID": 23,
      "Type": "0",
      "Chapter": "2",
      "Section": "7,9",
      "Wave1": "141:14,142:13",
      "Duration1": 6,
      "Wave2": "143:9,151:9",
      "Duration2": 6,
      "Wave3": "",
      "Duration3": "",
      "SuddenWave": "",
      "Duration4": "",
      "HPValue": 1.2,
      "DamageValue": "1"
    },
    {
      "ID": 24,
      "Type": "0",
      "Chapter": "2",
      "Section": "10",
      "Wave1": "305:26,306:27",
      "Duration1": 6,
      "Wave2": "313:19,314:19",
      "Duration2": 6,
      "Wave3": "",
      "Duration3": "",
      "SuddenWave": "",
      "Duration4": "",
      "HPValue": 1.2,
      "DamageValue": "1"
    },
    {
      "ID": 25,
      "Type": "0",
      "Chapter": "2",
      "Section": "10",
      "Wave1": "131:12,132:12",
      "Duration1": 6,
      "Wave2": "141:12,142:12",
      "Duration2": 6,
      "Wave3": "133:5,143:11",
      "Duration3": "6",
      "SuddenWave": "",
      "Duration4": "",
      "HPValue": 1.2,
      "DamageValue": "1"
    },
    {
      "ID": 26,
      "Type": "0",
      "Chapter": "3",
      "Section": "0,3",
      "Wave1": "301:41,302:35",
      "Duration1": 6,
      "Wave2": "301:23,303:17",
      "Duration2": 6,
      "Wave3": "",
      "Duration3": "",
      "SuddenWave": "",
      "Duration4": "",
      "HPValue": 1.2,
      "DamageValue": "1"
    },
    {
      "ID": 27,
      "Type": "0",
      "Chapter": "3",
      "Section": "0,3",
      "Wave1": "308:16:00",
      "Duration1": 6,
      "Wave2": "313:40,314:40",
      "Duration2": 6,
      "Wave3": "",
      "Duration3": "",
      "SuddenWave": "",
      "Duration4": "",
      "HPValue": 1.2,
      "DamageValue": "1"
    },
    {
      "ID": 28,
      "Type": "0",
      "Chapter": "3",
      "Section": "0,3",
      "Wave1": "307:25,308:25",
      "Duration1": 6,
      "Wave2": "309:22,310:22",
      "Duration2": 6,
      "Wave3": "",
      "Duration3": "",
      "SuddenWave": "",
      "Duration4": "",
      "HPValue": 1.2,
      "DamageValue": "1"
    },
    {
      "ID": 29,
      "Type": "0",
      "Chapter": "3",
      "Section": "4,6",
      "Wave1": "301:43,302:37",
      "Duration1": 6,
      "Wave2": "303:28,304:186",
      "Duration2": 6,
      "Wave3": "",
      "Duration3": "",
      "SuddenWave": "",
      "Duration4": "",
      "HPValue": 1.2,
      "DamageValue": "1"
    },
    {
      "ID": 30,
      "Type": "0",
      "Chapter": "3",
      "Section": "4,6",
      "Wave1": "309:37,310:37",
      "Duration1": 6,
      "Wave2": "307:29,308:29",
      "Duration2": 6,
      "Wave3": "",
      "Duration3": "",
      "SuddenWave": "",
      "Duration4": "",
      "HPValue": 1.2,
      "DamageValue": "1"
    },
    {
      "ID": 31,
      "Type": "0",
      "Chapter": "3",
      "Section": "4,6",
      "Wave1": "311:34,312:34",
      "Duration1": 6,
      "Wave2": "313:43,314:43",
      "Duration2": 6,
      "Wave3": "",
      "Duration3": "",
      "SuddenWave": "",
      "Duration4": "",
      "HPValue": 1.4,
      "DamageValue": "1"
    },
    {
      "ID": 32,
      "Type": "0",
      "Chapter": "3",
      "Section": "7,9",
      "Wave1": "305:60,306:59",
      "Duration1": 6,
      "Wave2": "313:59,314:59",
      "Duration2": 6,
      "Wave3": "",
      "Duration3": "",
      "SuddenWave": "",
      "Duration4": "",
      "HPValue": 1.4,
      "DamageValue": "1"
    },
    {
      "ID": 33,
      "Type": "0",
      "Chapter": "3",
      "Section": "7,9",
      "Wave1": "307:48,308:48",
      "Duration1": 6,
      "Wave2": "309:39,310:39",
      "Duration2": 6,
      "Wave3": "",
      "Duration3": "",
      "SuddenWave": "",
      "Duration4": "",
      "HPValue": 1.4,
      "DamageValue": "1"
    },
    {
      "ID": 34,
      "Type": "0",
      "Chapter": "3",
      "Section": "7,9",
      "Wave1": "311:39,312:39",
      "Duration1": 6,
      "Wave2": "305:48,306:48",
      "Duration2": 6,
      "Wave3": "",
      "Duration3": "",
      "SuddenWave": "",
      "Duration4": "",
      "HPValue": 1.4,
      "DamageValue": "1"
    },
    {
      "ID": 35,
      "Type": "0",
      "Chapter": "3",
      "Section": "10",
      "Wave1": "301:69,302:60",
      "Duration1": 6,
      "Wave2": "303:49,304:271",
      "Duration2": 6,
      "Wave3": "",
      "Duration3": "",
      "SuddenWave": "",
      "Duration4": "",
      "HPValue": 1.4,
      "DamageValue": "1"
    },
    {
      "ID": 36,
      "Type": "0",
      "Chapter": "3",
      "Section": "10",
      "Wave1": "311:53,312:54",
      "Duration1": 6,
      "Wave2": "307:44,310:44",
      "Duration2": 6,
      "Wave3": "",
      "Duration3": "",
      "SuddenWave": "",
      "Duration4": "",
      "HPValue": 1.4,
      "DamageValue": "1"
    },
    {
      "ID": 37,
      "Type": "0",
      "Chapter": "4",
      "Section": "0,3",
      "Wave1": "307:60,308:60",
      "Duration1": 6,
      "Wave2": "310:59,309:50",
      "Duration2": 6,
      "Wave3": "",
      "Duration3": "",
      "SuddenWave": "",
      "Duration4": "",
      "HPValue": 1.4,
      "DamageValue": "1"
    },
    {
      "ID": 38,
      "Type": "0",
      "Chapter": "4",
      "Section": "0,3",
      "Wave1": "311:53,312:52",
      "Duration1": 6,
      "Wave2": "305:61,306:61",
      "Duration2": 6,
      "Wave3": "",
      "Duration3": "",
      "SuddenWave": "",
      "Duration4": "",
      "HPValue": 1.4,
      "DamageValue": "1"
    },
    {
      "ID": 39,
      "Type": "0",
      "Chapter": "4",
      "Section": "0,3",
      "Wave1": "305:73,306:74",
      "Duration1": 6,
      "Wave2": "313:84,314:84",
      "Duration2": 6,
      "Wave3": "",
      "Duration3": "",
      "SuddenWave": "",
      "Duration4": "",
      "HPValue": 1.4,
      "DamageValue": "1"
    },
    {
      "ID": 40,
      "Type": "0",
      "Chapter": "4",
      "Section": "4,6",
      "Wave1": "308:74,309:74",
      "Duration1": 6,
      "Wave2": "307:55,310:54",
      "Duration2": 6,
      "Wave3": "",
      "Duration3": "",
      "SuddenWave": "",
      "Duration4": "",
      "HPValue": 1.4,
      "DamageValue": "1"
    },
    {
      "ID": 41,
      "Type": "0",
      "Chapter": "4",
      "Section": "4,6",
      "Wave1": "311:67,312:66",
      "Duration1": 6,
      "Wave2": "313:86,314:86",
      "Duration2": 6,
      "Wave3": "",
      "Duration3": "",
      "SuddenWave": "",
      "Duration4": "",
      "HPValue": 1.6,
      "DamageValue": "1"
    },
    {
      "ID": 42,
      "Type": "0",
      "Chapter": "4",
      "Section": "4,6",
      "Wave1": "143:35,142:30",
      "Duration1": 6,
      "Wave2": "305:91,306:91",
      "Duration2": 6,
      "Wave3": "",
      "Duration3": "",
      "SuddenWave": "",
      "Duration4": "",
      "HPValue": 1.6,
      "DamageValue": "1"
    },
    {
      "ID": 43,
      "Type": "0",
      "Chapter": "4",
      "Section": "7,9",
      "Wave1": "307:74,308:74",
      "Duration1": 6,
      "Wave2": "310:78,309:69",
      "Duration2": 6,
      "Wave3": "",
      "Duration3": "",
      "SuddenWave": "",
      "Duration4": "",
      "HPValue": 1.6,
      "DamageValue": "1"
    },
    {
      "ID": 44,
      "Type": "0",
      "Chapter": "4",
      "Section": "7,9",
      "Wave1": "305:100,306:100",
      "Duration1": 6,
      "Wave2": "313:100,314:100",
      "Duration2": 6,
      "Wave3": "",
      "Duration3": "",
      "SuddenWave": "",
      "Duration4": "",
      "HPValue": 1.6,
      "DamageValue": "1"
    },
    {
      "ID": 45,
      "Type": "0",
      "Chapter": "4",
      "Section": "7,9",
      "Wave1": "311:73,312:72",
      "Duration1": 6,
      "Wave2": "307:64,310:64",
      "Duration2": 6,
      "Wave3": "",
      "Duration3": "",
      "SuddenWave": "",
      "Duration4": "",
      "HPValue": 1.6,
      "DamageValue": "1"
    },
    {
      "ID": 46,
      "Type": "0",
      "Chapter": "4",
      "Section": "10",
      "Wave1": "308:87,309:87",
      "Duration1": 6,
      "Wave2": "310:79,307:71",
      "Duration2": 6,
      "Wave3": "",
      "Duration3": "",
      "SuddenWave": "",
      "Duration4": "",
      "HPValue": 1.6,
      "DamageValue": "1"
    },
    {
      "ID": 47,
      "Type": "0",
      "Chapter": "4",
      "Section": "10",
      "Wave1": "322:24:00",
      "Duration1": 6,
      "Wave2": "313:111,314:92",
      "Duration2": 6,
      "Wave3": "",
      "Duration3": "",
      "SuddenWave": "",
      "Duration4": "",
      "HPValue": 1.6,
      "DamageValue": "1"
    },
    {
      "ID": 48,
      "Type": "0",
      "Chapter": "5",
      "Section": "0,3",
      "Wave1": "307:79,308:79",
      "Duration1": 6,
      "Wave2": "309:75,310:76",
      "Duration2": 6,
      "Wave3": "",
      "Duration3": "",
      "SuddenWave": "",
      "Duration4": "",
      "HPValue": 1.6,
      "DamageValue": "1"
    },
    {
      "ID": 49,
      "Type": "0",
      "Chapter": "5",
      "Section": "0,3",
      "Wave1": "311:73,312:72",
      "Duration1": 6,
      "Wave2": "305:81,306:80",
      "Duration2": 6,
      "Wave3": "",
      "Duration3": "",
      "SuddenWave": "",
      "Duration4": "",
      "HPValue": 1.6,
      "DamageValue": "1"
    },
    {
      "ID": 50,
      "Type": "0",
      "Chapter": "5",
      "Section": "0,3",
      "Wave1": "313:125,314:125",
      "Duration1": 6,
      "Wave2": "307:75,308:76",
      "Duration2": 6,
      "Wave3": "",
      "Duration3": "",
      "SuddenWave": "",
      "Duration4": "",
      "HPValue": 1.6,
      "DamageValue": "1"
    },
    {
      "ID": 51,
      "Type": "0",
      "Chapter": "5",
      "Section": "4,6",
      "Wave1": "305:108,306:107",
      "Duration1": 6,
      "Wave2": "313:116,314:117",
      "Duration2": 6,
      "Wave3": "",
      "Duration3": "",
      "SuddenWave": "",
      "Duration4": "",
      "HPValue": 1.8,
      "DamageValue": "1"
    },
    {
      "ID": 52,
      "Type": "0",
      "Chapter": "5",
      "Section": "4,6",
      "Wave1": "143:46,142:40",
      "Duration1": 6,
      "Wave2": "306:115,305:106",
      "Duration2": 6,
      "Wave3": "",
      "Duration3": "",
      "SuddenWave": "",
      "Duration4": "",
      "HPValue": 1.8,
      "DamageValue": "1"
    },
    {
      "ID": 53,
      "Type": "0",
      "Chapter": "5",
      "Section": "4,6",
      "Wave1": "307:84,308:84",
      "Duration1": 6,
      "Wave2": "310:83,309:76",
      "Duration2": 6,
      "Wave3": "",
      "Duration3": "",
      "SuddenWave": "",
      "Duration4": "",
      "HPValue": 1.8,
      "DamageValue": "1"
    },
    {
      "ID": 54,
      "Type": "0",
      "Chapter": "5",
      "Section": "7,9",
      "Wave1": "308:95,309:95",
      "Duration1": 6,
      "Wave2": "307:77,310:78",
      "Duration2": 6,
      "Wave3": "",
      "Duration3": "",
      "SuddenWave": "",
      "Duration4": "",
      "HPValue": 1.8,
      "DamageValue": "1"
    },
    {
      "ID": 55,
      "Type": "0",
      "Chapter": "5",
      "Section": "7,9",
      "Wave1": "311:94,312:94",
      "Duration1": 6,
      "Wave2": "313:106,314:105",
      "Duration2": 6,
      "Wave3": "",
      "Duration3": "",
      "SuddenWave": "",
      "Duration4": "",
      "HPValue": 1.8,
      "DamageValue": "1"
    },
    {
      "ID": 56,
      "Type": "0",
      "Chapter": "5",
      "Section": "7,9",
      "Wave1": "305:129,306:128",
      "Duration1": 6,
      "Wave2": "141:86,143:68",
      "Duration2": 6,
      "Wave3": "",
      "Duration3": "",
      "SuddenWave": "",
      "Duration4": "",
      "HPValue": 1.8,
      "DamageValue": "1"
    },
    {
      "ID": 57,
      "Type": "0",
      "Chapter": "5",
      "Section": "10",
      "Wave1": "307:99,310:97",
      "Duration1": 6,
      "Wave2": "305:98,306:98",
      "Duration2": 6,
      "Wave3": "",
      "Duration3": "",
      "SuddenWave": "",
      "Duration4": "",
      "HPValue": 1.8,
      "DamageValue": "1"
    },
    {
      "ID": 58,
      "Type": "0",
      "Chapter": "5",
      "Section": "10",
      "Wave1": "311:103,312:104",
      "Duration1": 6,
      "Wave2": "313:101,314:104",
      "Duration2": 6,
      "Wave3": "",
      "Duration3": "",
      "SuddenWave": "",
      "Duration4": "",
      "HPValue": 1.8,
      "DamageValue": "1"
    }
  ]
}