{
  "data": [
    {
      "ID": 1,
      "SynergyID": 1,
      "Name": "SYNERGY_1",
      "Icon": "synergy_1",
      "SynergySkillIcon": "SynergySkill_01",
      "Condition": 3,
      "Desc": "SYNERGY_1_DESC",
      "SynergyType": 1,
      "Value": 310001
    },
    {
      "ID": 2,
      "SynergyID": 2,
      "Name": "SYNERGY_2",
      "Icon": "synergy_2",
      "SynergySkillIcon": "SynergySkill_02",
      "Condition": 3,
      "Desc": "SYNERGY_2_DESC",
      "SynergyType": 2,
      "Value": 310002
    },
    {
      "ID": 3,
      "SynergyID": 3,
      "Name": "SYNERGY_3",
      "Icon": "synergy_3",
      "SynergySkillIcon": "SynergySkill_03",
      "Condition": 2,
      "Desc": "SYNERGY_1_DESC",
      "SynergyType": 4,
      "Value": 310003
    },
    {
      "ID": 4,
      "SynergyID": 4,
      "Name": "SYNERGY_4",
      "Icon": "synergy_4",
      "SynergySkillIcon": "SynergySkill_04",
      "Condition": 2,
      "Desc": "SYNERGY_1_DESC",
      "SynergyType": 1,
      "Value": 310004
    },
    {
      "ID": 5,
      "SynergyID": 5,
      "Name": "SYNERGY_5",
      "Icon": "synergy_5",
      "SynergySkillIcon": "SynergySkill_05",
      "Condition": 2,
      "Desc": "SYNERGY_2_DESC",
      "SynergyType": 3,
      "Value": 320001
    },
    {
      "ID": 6,
      "SynergyID": 6,
      "Name": "SYNERGY_6",
      "Icon": "synergy_6",
      "SynergySkillIcon": "SynergySkill_06",
      "Condition": 3,
      "Desc": "SYNERGY_2_DESC",
      "SynergyType": 2,
      "Value": 320002
    },
    {
      "ID": 7,
      "SynergyID": 7,
      "Name": "SYNERGY_7",
      "Icon": "synergy_7",
      "SynergySkillIcon": "SynergySkill_07",
      "Condition": 2,
      "Desc": "SYNERGY_2_DESC",
      "SynergyType": 1,
      "Value": 320003
    },
    {
      "ID": 8,
      "SynergyID": 8,
      "Name": "SYNERGY_8",
      "Icon": "synergy_8",
      "SynergySkillIcon": "SynergySkill_08",
      "Condition": 3,
      "Desc": "SYNERGY_2_DESC",
      "SynergyType": 6,
      "Value": 2
    },
    {
      "ID": 9,
      "SynergyID": 9,
      "Name": "SYNERGY_9",
      "Icon": "synergy_9",
      "SynergySkillIcon": "SynergySkill_09",
      "Condition": 4,
      "Desc": "SYNERGY_3_DESC",
      "SynergyType": 1,
      "Value": 330001
    },
    {
      "ID": 10,
      "SynergyID": 10,
      "Name": "SYNERGY_10",
      "Icon": "synergy_10",
      "SynergySkillIcon": "SynergySkill_10",
      "Condition": 3,
      "Desc": "SYNERGY_3_DESC",
      "SynergyType": 4,
      "Value": 330002
    },
    {
      "ID": 11,
      "SynergyID": 11,
      "Name": "SYNERGY_11",
      "Icon": "synergy_11",
      "SynergySkillIcon": "SynergySkill_11",
      "Condition": 3,
      "Desc": "SYNERGY_3_DESC",
      "SynergyType": 2,
      "Value": 330003
    },
    {
      "ID": 12,
      "SynergyID": 12,
      "Name": "SYNERGY_12",
      "Icon": "synergy_12",
      "SynergySkillIcon": "SynergySkill_12",
      "Condition": 4,
      "Desc": "SYNERGY_3_DESC",
      "SynergyType": 1,
      "Value": 340001
    },
    {
      "ID": 13,
      "SynergyID": 13,
      "Name": "SYNERGY_13",
      "Icon": "synergy_13",
      "SynergySkillIcon": "SynergySkill_13",
      "Condition": 4,
      "Desc": "SYNERGY_4_DESC",
      "SynergyType": 4,
      "Value": 340002
    },
    {
      "ID": 14,
      "SynergyID": 14,
      "Name": "SYNERGY_14",
      "Icon": "synergy_14",
      "SynergySkillIcon": "SynergySkill_14",
      "Condition": 2,
      "Desc": "SYNERGY_4_DESC",
      "SynergyType": 1,
      "Value": 340003
    },
    {
      "ID": 15,
      "SynergyID": 15,
      "Name": "SYNERGY_15",
      "Icon": "synergy_15",
      "SynergySkillIcon": "SynergySkill_15",
      "Condition": 2,
      "Desc": "SYNERGY_4_DESC",
      "SynergyType": 4,
      "Value": 350001
    },
    {
      "ID": 16,
      "SynergyID": 16,
      "Name": "SYNERGY_16",
      "Icon": "synergy_16",
      "SynergySkillIcon": "SynergySkill_16",
      "Condition": 2,
      "Desc": "SYNERGY_4_DESC",
      "SynergyType": 4,
      "Value": 350002
    },
    {
      "ID": 17,
      "SynergyID": 17,
      "Name": "SYNERGY_17",
      "Icon": "synergy_17",
      "SynergySkillIcon": "SynergySkill_17",
      "Condition": 3,
      "Desc": "SYNERGY_5_DESC",
      "SynergyType": 4,
      "Value": 350003
    },
    {
      "ID": 18,
      "SynergyID": 18,
      "Name": "SYNERGY_18",
      "Icon": "synergy_18",
      "SynergySkillIcon": "SynergySkill_18",
      "Condition": 3,
      "Desc": "SYNERGY_5_DESC",
      "SynergyType": 1,
      "Value": 360004
    },
    {
      "ID": 19,
      "SynergyID": 19,
      "Name": "SYNERGY_19",
      "Icon": "synergy_19",
      "SynergySkillIcon": "SynergySkill_19",
      "Condition": 3,
      "Desc": "SYNERGY_5_DESC",
      "SynergyType": 2,
      "Value": 360001
    },
    {
      "ID": 20,
      "SynergyID": 20,
      "Name": "SYNERGY_20",
      "Icon": "synergy_20",
      "SynergySkillIcon": "SynergySkill_20",
      "Condition": 4,
      "Desc": "SYNERGY_5_DESC",
      "SynergyType": 4,
      "Value": 360002
    },
    {
      "ID": 21,
      "SynergyID": 21,
      "Name": "SYNERGY_21",
      "Icon": "synergy_21",
      "SynergySkillIcon": "SynergySkill_21",
      "Condition": 3,
      "Desc": "SYNERGY_6_DESC",
      "SynergyType": 5,
      "Value": 75
    },
    {
      "ID": 22,
      "SynergyID": 22,
      "Name": "SYNERGY_22",
      "Icon": "synergy_22",
      "SynergySkillIcon": "SynergySkill_22",
      "Condition": 4,
      "Desc": "SYNERGY_6_DESC",
      "SynergyType": 3,
      "Value": 370001
    },
    {
      "ID": 23,
      "SynergyID": 23,
      "Name": "SYNERGY_23",
      "Icon": "synergy_23",
      "SynergySkillIcon": "SynergySkill_23",
      "Condition": 3,
      "Desc": "SYNERGY_6_DESC",
      "SynergyType": 1,
      "Value": 370002
    },
    {
      "ID": 24,
      "SynergyID": 24,
      "Name": "SYNERGY_24",
      "Icon": "synergy_24",
      "SynergySkillIcon": "SynergySkill_24",
      "Condition": 3,
      "Desc": "SYNERGY_6_DESC",
      "SynergyType": 1,
      "Value": 370003
    }
  ]
}